ferveo-0.1.13.dist-info/METADATA
ferveo-0.1.13.dist-info/WHEEL
ferveo-0.1.13.dist-info/license_files/LICENSE
ferveo_py/__init__.py
ferveo_py/ferveo_py.cpython-310-x86_64-linux-gnu.so
ferveo-0.1.13.dist-info/RECORD
