Metadata-Version: 2.1
Name: ferveo
Version: 0.1.13
Classifier: Programming Language :: Rust
Classifier: Programming Language :: Python :: Implementation :: CPython
Classifier: Programming Language :: Python :: Implementation :: PyPy
License-File: LICENSE
Author: Piotr Roslaniec <p.roslaniec@gmail.com>
Author-email: Piotr Roslaniec <p.roslaniec@gmail.com>
Requires-Python: >=3.7
